src/Py_RHT/__init__.py
src/Py_RHT/bin.py
src/Py_RHT/crypto/__init__.py
src/Py_RHT/crypto/b64.py
src/Py_RHT/crypto/bitshift.py
src/Py_RHT/crypto/decimal.py
src/Py_RHT/crypto/reverse.py
src/Py_RHT/crypto/xor.py
src/Py_RHT/forensics/__init__.py
src/Py_RHT/forensics/strings.py
src/Py_RHT/programming/__init__.py
Py_RHT-0.0.1.dist-info/LICENSE
Py_RHT-0.0.1.dist-info/METADATA
Py_RHT-0.0.1.dist-info/WHEEL
Py_RHT-0.0.1.dist-info/top_level.txt
Py_RHT-0.0.1.dist-info/RECORD
