Metadata-Version: 2.1
Name: Py_RHT
Version: 0.0.1
Summary: Python tools for forensics and crypto
Author: Jay Feldman
Author-email: <feldmanjay@gmail.com>
Classifier: Programming Language :: Python :: 3
Classifier: License :: OSI Approved :: GNU General Public License v3 or later (GPLv3+)
Classifier: Operating System :: OS Independent
Classifier: Development Status :: 1 - Planning
License-File: LICENSE
